jupyterlab_theme_hale/__init__.py
jupyterlab_theme_hale/_version.py
jupyterlab_theme_hale/labextension/package.json
jupyterlab_theme_hale/labextension/static/568.f36856d2795db4d89a2b.js
jupyterlab_theme_hale/labextension/static/remoteEntry.268288225d6cd77be361.js
jupyterlab_theme_hale/labextension/static/remoteEntry.956ab1b1be65627ff041.js
jupyterlab_theme_hale/labextension/static/remoteEntry.a12af56848629fab3bd9.js
jupyterlab_theme_hale/labextension/static/style.js
jupyterlab_theme_hale/labextension/themes/jupyterlab-theme-hale/index.css
jupyterlab_theme_hale/labextension/themes/jupyterlab-theme-hale/index.js
jupyterlab_theme_hale-0.1.3.data/data/share/jupyter/labextensions/jupyterlab-theme-hale/install.json
jupyterlab_theme_hale-0.1.3.data/data/share/jupyter/labextensions/jupyterlab-theme-hale/package.json
jupyterlab_theme_hale-0.1.3.data/data/share/jupyter/labextensions/jupyterlab-theme-hale/static/568.f36856d2795db4d89a2b.js
jupyterlab_theme_hale-0.1.3.data/data/share/jupyter/labextensions/jupyterlab-theme-hale/static/remoteEntry.956ab1b1be65627ff041.js
jupyterlab_theme_hale-0.1.3.data/data/share/jupyter/labextensions/jupyterlab-theme-hale/static/style.js
jupyterlab_theme_hale-0.1.3.data/data/share/jupyter/labextensions/jupyterlab-theme-hale/themes/jupyterlab-theme-hale/index.css
jupyterlab_theme_hale-0.1.3.data/data/share/jupyter/labextensions/jupyterlab-theme-hale/themes/jupyterlab-theme-hale/index.js
jupyterlab_theme_hale-0.1.3.dist-info/LICENSE
jupyterlab_theme_hale-0.1.3.dist-info/METADATA
jupyterlab_theme_hale-0.1.3.dist-info/WHEEL
jupyterlab_theme_hale-0.1.3.dist-info/top_level.txt
jupyterlab_theme_hale-0.1.3.dist-info/RECORD
